templ8/__init__.py
templ8/blessing.py
templ8/divine.py
templ8/genesis.py
templ8/help_args.py
templ8/main.py
templ8/neo.py
templ8/pandoc.py
templ8/programstate.py
templ8/radio.py
templ8.py-0.1.0b25.dist-info/LICENSE
templ8.py-0.1.0b25.dist-info/METADATA
templ8.py-0.1.0b25.dist-info/WHEEL
templ8.py-0.1.0b25.dist-info/entry_points.txt
templ8.py-0.1.0b25.dist-info/top_level.txt
templ8.py-0.1.0b25.dist-info/RECORD
