Metadata-Version: 2.1
Name: templ8.py
Version: 0.1.0b25
Summary: Templ8.py is a static site generator
Home-page: https://github.com/Lilith-In-Starlight/improved-templ8.py
Author: Katie Ampersand
Author-email: katie-and@ampersandia.net
Classifier: Programming Language :: Python :: 3.6
Classifier: Development Status :: 4 - Beta
Requires-Python: >=3.6
License-File: LICENSE
Requires-Dist: textile
Requires-Dist: pypandoc
Requires-Dist: maturin
Requires-Dist: pykami
